{
    "data": {
        "train_path": "../input/house/train.csv",
        "test_path": "../input/house/test.csv",
        "pred_col": "SalePrice",
        "id_col": "Id",
        "random": false,
        "adversarial": {
            "model": "log_reg",
            "scoring": "accuracy",
            "cv": 3,
            "n_jobs": -1,
            "params" : {
                "penalty": ["l1", "l2"],
                "C": [1, 2, 3, 4, 5]
            }
        },
        "adversarial": {
        }
    },
    "translate": {
        "adhoc": {
            "myfunc": false,
            "methods": [
            ]
        },
        "del": [
        ],
        "category": [
        ],
        "dimension": 62
    },
    "fit": {
        "pre": "log",
        "mode": "reg",
        "model": "svr",
        "modelname": "house",
        "scoring": "neg_mean_squared_error",
        "cv": 5,
        "n_jobs": -1,
        "fit_params" : {
        },
        "params" : {
            "C": [1],
            "degree": [1],
            "kernel": ["poly"]
        }
    },
    "notify": {
        "slack": "https://hooks.slack.com/services/hogehoge"
    }
}
